setup.cfg
setup.py
flast/__init__.py
flast/app.py
flast/views.py
flast.egg-info/PKG-INFO
flast.egg-info/SOURCES.txt
flast.egg-info/dependency_links.txt
flast.egg-info/requires.txt
flast.egg-info/top_level.txt
flast/bin/flast-init.py
flast/templates/__init__.py
flast/templates/app.py
flast/templates/settings.py
flast/templates/urls.py
flast/templates/views.py