Metadata-Version: 1.0
Name: flast
Version: 1.1
Summary: Werkzeug based micro-framework 
Home-page: UNKNOWN
Author: Yohann Gabory
Author-email: yohann@gabory.fr
License: UNKNOWN
Platform: UNKNOWN
